heiplanet_data/__init__.py
heiplanet_data/era5_settings.json
heiplanet_data/inout.py
heiplanet_data/isimip_settings.json
heiplanet_data/preprocess.py
heiplanet_data/script.py
heiplanet_data/setting_schema.json
heiplanet_data/utils.py
heiplanet_data/test/conftest.py
heiplanet_data/test/test_inout.py
heiplanet_data/test/test_preprocess.py
heiplanet_data/test/test_utils.py
heiplanet_data/test/data/.keep
heiplanet_data-0.1.0.dist-info/METADATA
heiplanet_data-0.1.0.dist-info/WHEEL
heiplanet_data-0.1.0.dist-info/licenses/LICENSE
heiplanet_data-0.1.0.dist-info/RECORD
