Metadata-Version: 2.4
Name: heiplanet-data
Version: 0.1.0
Summary: Data processing pipeline for heiplanet
Project-URL: Homepage, https://github.com/ssciwr/heiplanet-data
Project-URL: Issues, https://github.com/ssciwr/heiplanet-data/issues
Author-email: Tuyen Le <ssc@iwr.uni-heidelberg.de>, Inga Ulusoy <ssc@iwr.uni-heidelberg.de>
License-Expression: MIT
License-File: LICENSE
Classifier: Operating System :: OS Independent
Classifier: Programming Language :: Python :: 3
Requires-Python: >=3.11
Requires-Dist: cdo
Requires-Dist: cdsapi
Requires-Dist: cfgrib
Requires-Dist: dask[complete]
Requires-Dist: exactextract
Requires-Dist: geopandas
Requires-Dist: isimip-client
Requires-Dist: jupyter
Requires-Dist: matplotlib
Requires-Dist: netcdf4
Requires-Dist: rioxarray
Requires-Dist: scipy
Requires-Dist: xagg
Requires-Dist: xarray
Requires-Dist: xesmf
Provides-Extra: dev
Requires-Dist: pre-commit; extra == 'dev'
Requires-Dist: pytest; extra == 'dev'
Requires-Dist: pytest-cov; extra == 'dev'
Provides-Extra: docs
Requires-Dist: mkdocs-gen-files; extra == 'docs'
Requires-Dist: mkdocs-glightbox; extra == 'docs'
Requires-Dist: mkdocs-include-markdown-plugin; extra == 'docs'
Requires-Dist: mkdocs-jupyter; extra == 'docs'
Requires-Dist: mkdocs-literate-nav; extra == 'docs'
Requires-Dist: mkdocs-material; extra == 'docs'
Requires-Dist: mkdocs-minify-plugin; extra == 'docs'
Requires-Dist: mkdocs-section-index; extra == 'docs'
Requires-Dist: mkdocstrings-python; extra == 'docs'
